{
    "key": "group_5f296d947ba89",
    "title": "Flex Sections",
    "fields": [
        {
            "key": "field_5f296dcbe2111",
            "label": "Sections",
            "name": "sections",
            "type": "flexible_content",
            "instructions": "",
            "required": 0,
            "conditional_logic": 0,
            "wrapper": {
                "width": "",
                "class": "",
                "id": ""
            },
            "layouts": {
                "layout_5f31429d62285": {
                    "key": "layout_5f31429d62285",
                    "name": "header",
                    "label": "Page Header",
                    "display": "block",
                    "sub_fields": [
                        {
                            "key": "field_5f3142b662286",
                            "label": "Section",
                            "name": "section",
                            "type": "clone",
                            "instructions": "",
                            "required": 0,
                            "conditional_logic": 0,
                            "wrapper": {
                                "width": "",
                                "class": "",
                                "id": ""
                            },
                            "clone": [
                                "group_5f31404436653"
                            ],
                            "display": "seamless",
                            "layout": "block",
                            "prefix_label": 0,
                            "prefix_name": 0
                        }
                    ],
                    "min": "",
                    "max": ""
                },
                "layout_5f296dd0708d2": {
                    "key": "layout_5f296dd0708d2",
                    "name": "text",
                    "label": "Text",
                    "display": "block",
                    "sub_fields": [
                        {
                            "key": "field_5f2976142a7b4",
                            "label": "Section",
                            "name": "section",
                            "type": "clone",
                            "instructions": "",
                            "required": 0,
                            "conditional_logic": 0,
                            "wrapper": {
                                "width": "",
                                "class": "",
                                "id": ""
                            },
                            "clone": [
                                "group_5f2975c1058e6"
                            ],
                            "display": "seamless",
                            "layout": "block",
                            "prefix_label": 0,
                            "prefix_name": 0
                        }
                    ],
                    "min": "",
                    "max": ""
                },
                "layout_5f40066a15c8b": {
                    "key": "layout_5f40066a15c8b",
                    "name": "columns",
                    "label": "Info Columns",
                    "display": "block",
                    "sub_fields": [
                        {
                            "key": "field_5f40067215c8c",
                            "label": "Section",
                            "name": "section",
                            "type": "clone",
                            "instructions": "",
                            "required": 0,
                            "conditional_logic": 0,
                            "wrapper": {
                                "width": "",
                                "class": "",
                                "id": ""
                            },
                            "clone": [
                                "group_5f3ff79d408f5"
                            ],
                            "display": "seamless",
                            "layout": "block",
                            "prefix_label": 0,
                            "prefix_name": 0
                        }
                    ],
                    "min": "",
                    "max": ""
                },
                "layout_5f36ba4596ac3": {
                    "key": "layout_5f36ba4596ac3",
                    "name": "image",
                    "label": "Full-Width Image",
                    "display": "block",
                    "sub_fields": [
                        {
                            "key": "field_5f36ba5f96ac4",
                            "label": "Section",
                            "name": "section",
                            "type": "clone",
                            "instructions": "",
                            "required": 0,
                            "conditional_logic": 0,
                            "wrapper": {
                                "width": "",
                                "class": "",
                                "id": ""
                            },
                            "clone": [
                                "group_5f36ad5ee22fd"
                            ],
                            "display": "seamless",
                            "layout": "block",
                            "prefix_label": 0,
                            "prefix_name": 0
                        }
                    ],
                    "min": "",
                    "max": ""
                },
                "layout_5f36dcfc4c35a": {
                    "key": "layout_5f36dcfc4c35a",
                    "name": "slider",
                    "label": "Image Slider",
                    "display": "block",
                    "sub_fields": [
                        {
                            "key": "field_5f36dd114c35b",
                            "label": "Section",
                            "name": "section",
                            "type": "clone",
                            "instructions": "",
                            "required": 0,
                            "conditional_logic": 0,
                            "wrapper": {
                                "width": "",
                                "class": "",
                                "id": ""
                            },
                            "clone": [
                                "group_5f36da1d1e003"
                            ],
                            "display": "seamless",
                            "layout": "block",
                            "prefix_label": 0,
                            "prefix_name": 0
                        }
                    ],
                    "min": "",
                    "max": ""
                },
                "layout_5f319ac6e7359": {
                    "key": "layout_5f319ac6e7359",
                    "name": "gallery_masonry",
                    "label": "Image Gallery (Masonry Grid)",
                    "display": "block",
                    "sub_fields": [
                        {
                            "key": "field_5f319adbe735a",
                            "label": "Section",
                            "name": "section",
                            "type": "clone",
                            "instructions": "",
                            "required": 0,
                            "conditional_logic": 0,
                            "wrapper": {
                                "width": "",
                                "class": "",
                                "id": ""
                            },
                            "clone": [
                                "group_5f319940cf2f2"
                            ],
                            "display": "seamless",
                            "layout": "block",
                            "prefix_label": 0,
                            "prefix_name": 0
                        }
                    ],
                    "min": "",
                    "max": ""
                },
                "layout_5f32a966064ae": {
                    "key": "layout_5f32a966064ae",
                    "name": "gallery_rows",
                    "label": "Image Gallery (Rows)",
                    "display": "block",
                    "sub_fields": [
                        {
                            "key": "field_5f32a96f064af",
                            "label": "Section",
                            "name": "section",
                            "type": "clone",
                            "instructions": "",
                            "required": 0,
                            "conditional_logic": 0,
                            "wrapper": {
                                "width": "",
                                "class": "",
                                "id": ""
                            },
                            "clone": [
                                "group_5f32a910f393b"
                            ],
                            "display": "seamless",
                            "layout": "block",
                            "prefix_label": 0,
                            "prefix_name": 0
                        }
                    ],
                    "min": "",
                    "max": ""
                },
                "layout_5f34268e05eaf": {
                    "key": "layout_5f34268e05eaf",
                    "name": "embed",
                    "label": "Embedded Video",
                    "display": "block",
                    "sub_fields": [
                        {
                            "key": "field_5f34269a05eb0",
                            "label": "Section",
                            "name": "section",
                            "type": "clone",
                            "instructions": "",
                            "required": 0,
                            "conditional_logic": 0,
                            "wrapper": {
                                "width": "",
                                "class": "",
                                "id": ""
                            },
                            "clone": [
                                "group_5f3424e3bc01d"
                            ],
                            "display": "seamless",
                            "layout": "block",
                            "prefix_label": 0,
                            "prefix_name": 0
                        }
                    ],
                    "min": "",
                    "max": ""
                },
                "layout_5f3c0766189d5": {
                    "key": "layout_5f3c0766189d5",
                    "name": "blocks",
                    "label": "Text with Image",
                    "display": "block",
                    "sub_fields": [
                        {
                            "key": "field_5f3c077a189d6",
                            "label": "Section",
                            "name": "section",
                            "type": "clone",
                            "instructions": "",
                            "required": 0,
                            "conditional_logic": 0,
                            "wrapper": {
                                "width": "",
                                "class": "",
                                "id": ""
                            },
                            "clone": [
                                "group_5f3bf9b909635"
                            ],
                            "display": "seamless",
                            "layout": "block",
                            "prefix_label": 0,
                            "prefix_name": 0
                        }
                    ],
                    "min": "",
                    "max": ""
                },
                "layout_5f3eacb37fc6f": {
                    "key": "layout_5f3eacb37fc6f",
                    "name": "cta",
                    "label": "Call to Action",
                    "display": "block",
                    "sub_fields": [
                        {
                            "key": "field_5f3eacb97fc70",
                            "label": "Section",
                            "name": "section",
                            "type": "clone",
                            "instructions": "",
                            "required": 0,
                            "conditional_logic": 0,
                            "wrapper": {
                                "width": "",
                                "class": "",
                                "id": ""
                            },
                            "clone": [
                                "group_5f3eab56c1576"
                            ],
                            "display": "seamless",
                            "layout": "block",
                            "prefix_label": 0,
                            "prefix_name": 0
                        }
                    ],
                    "min": "",
                    "max": ""
                },
                "layout_5f3ec716f871c": {
                    "key": "layout_5f3ec716f871c",
                    "name": "logos",
                    "label": "Logos",
                    "display": "block",
                    "sub_fields": [
                        {
                            "key": "field_5f3ec725f871d",
                            "label": "Section",
                            "name": "section",
                            "type": "clone",
                            "instructions": "",
                            "required": 0,
                            "conditional_logic": 0,
                            "wrapper": {
                                "width": "",
                                "class": "",
                                "id": ""
                            },
                            "clone": [
                                "group_5f3ec4e425875"
                            ],
                            "display": "seamless",
                            "layout": "block",
                            "prefix_label": 0,
                            "prefix_name": 0
                        }
                    ],
                    "min": "",
                    "max": ""
                },
                "layout_5f46708476753": {
                    "key": "layout_5f46708476753",
                    "name": "testimonials",
                    "label": "Testimonials",
                    "display": "block",
                    "sub_fields": [
                        {
                            "key": "field_5f4670b976754",
                            "label": "Section",
                            "name": "section",
                            "type": "clone",
                            "instructions": "",
                            "required": 0,
                            "conditional_logic": 0,
                            "wrapper": {
                                "width": "",
                                "class": "",
                                "id": ""
                            },
                            "clone": [
                                "group_5f466e682a0ee"
                            ],
                            "display": "seamless",
                            "layout": "block",
                            "prefix_label": 0,
                            "prefix_name": 0
                        }
                    ],
                    "min": "",
                    "max": ""
                },
                "layout_5f46a3dac487c": {
                    "key": "layout_5f46a3dac487c",
                    "name": "tiles",
                    "label": "Tiles",
                    "display": "block",
                    "sub_fields": [
                        {
                            "key": "field_5f46a3e0c487d",
                            "label": "Section",
                            "name": "section",
                            "type": "clone",
                            "instructions": "",
                            "required": 0,
                            "conditional_logic": 0,
                            "wrapper": {
                                "width": "",
                                "class": "",
                                "id": ""
                            },
                            "clone": [
                                "group_5f46a2c378980"
                            ],
                            "display": "seamless",
                            "layout": "block",
                            "prefix_label": 0,
                            "prefix_name": 0
                        }
                    ],
                    "min": "",
                    "max": ""
                },
                "layout_5f4fdad137628": {
                    "key": "layout_5f4fdad137628",
                    "name": "posts",
                    "label": "Posts",
                    "display": "block",
                    "sub_fields": [
                        {
                            "key": "field_5f4fdad637629",
                            "label": "Section",
                            "name": "section",
                            "type": "clone",
                            "instructions": "",
                            "required": 0,
                            "conditional_logic": 0,
                            "wrapper": {
                                "width": "",
                                "class": "",
                                "id": ""
                            },
                            "clone": [
                                "group_5f4fd7a5e3b6e"
                            ],
                            "display": "seamless",
                            "layout": "block",
                            "prefix_label": 0,
                            "prefix_name": 0
                        }
                    ],
                    "min": "",
                    "max": ""
                },
                "layout_5f59289ad7513": {
                    "key": "layout_5f59289ad7513",
                    "name": "events",
                    "label": "Events",
                    "display": "block",
                    "sub_fields": [
                        {
                            "key": "field_5f59289fd7514",
                            "label": "Section",
                            "name": "section",
                            "type": "clone",
                            "instructions": "",
                            "required": 0,
                            "conditional_logic": 0,
                            "wrapper": {
                                "width": "",
                                "class": "",
                                "id": ""
                            },
                            "clone": [
                                "group_5f5927e1a46f9"
                            ],
                            "display": "seamless",
                            "layout": "block",
                            "prefix_label": 0,
                            "prefix_name": 0
                        }
                    ],
                    "min": "",
                    "max": ""
                },
                "layout_5f6223dee7950": {
                    "key": "layout_5f6223dee7950",
                    "name": "form",
                    "label": "Form",
                    "display": "block",
                    "sub_fields": [
                        {
                            "key": "field_5f6223e3e7951",
                            "label": "Section",
                            "name": "section",
                            "type": "clone",
                            "instructions": "",
                            "required": 0,
                            "conditional_logic": 0,
                            "wrapper": {
                                "width": "",
                                "class": "",
                                "id": ""
                            },
                            "clone": [
                                "group_5f62156b5de55"
                            ],
                            "display": "seamless",
                            "layout": "block",
                            "prefix_label": 0,
                            "prefix_name": 0
                        }
                    ],
                    "min": "",
                    "max": ""
                },
                "layout_5f34211fcc6ff": {
                    "key": "layout_5f34211fcc6ff",
                    "name": "divider",
                    "label": "Divider",
                    "display": "block",
                    "sub_fields": [
                        {
                            "key": "field_5f342128cc700",
                            "label": "Section",
                            "name": "section",
                            "type": "clone",
                            "instructions": "",
                            "required": 0,
                            "conditional_logic": 0,
                            "wrapper": {
                                "width": "",
                                "class": "",
                                "id": ""
                            },
                            "clone": [
                                "group_5f341d4138432"
                            ],
                            "display": "seamless",
                            "layout": "block",
                            "prefix_label": 0,
                            "prefix_name": 0
                        }
                    ],
                    "min": "",
                    "max": ""
                }
            },
            "button_label": "Add Section",
            "min": "",
            "max": ""
        }
    ],
    "location": [
        [
            {
                "param": "post_type",
                "operator": "==",
                "value": "post"
            }
        ]
    ],
    "menu_order": 0,
    "position": "normal",
    "style": "default",
    "label_placement": "top",
    "instruction_placement": "label",
    "hide_on_screen": "",
    "active": false,
    "description": "",
    "modified": 1600267259
}